LICENSE
lgg/__init__.py
lgg/_logger.py
lgg-0.3.0.dist-info/LICENSE
lgg-0.3.0.dist-info/METADATA
lgg-0.3.0.dist-info/WHEEL
lgg-0.3.0.dist-info/RECORD
