Metadata-Version: 2.1
Name: lgg
Version: 0.3.0
Summary: A simple yet fancy logger for Python scripts
Home-page: https://github.com/blurry-mood/python-logger
License: MIT
Keywords: Python,Logger,Fancy Logger
Author: Ayoub Assis
Author-email: assis.ayoub@gmail.com
Requires-Python: >=3.8,<4.0
Classifier: License :: OSI Approved :: MIT License
Classifier: Programming Language :: Python :: 3
Classifier: Programming Language :: Python :: 3.8
Classifier: Programming Language :: Python :: 3.9
Classifier: Programming Language :: Python :: 3.10
Classifier: Programming Language :: Python :: 3.11
Classifier: Programming Language :: Python :: 3.12
Project-URL: Repository, https://github.com/blurry-mood/python-logger
